{"$type":"List`1","$values":[{"$id":"1","$type":"ProjectOptionEntry","key":"NetworkCollapsed","context":"{2232342-11196}","value":false},{"$id":"2","$type":"ProjectOptionEntry","key":"NetworkCollapsed","context":"{2232342-11197}","value":false},{"$id":"3","$type":"ProjectOptionEntry","key":"RestoreNetworkStates","context":"{2232321-11194}","value":true},{"$id":"4","$type":"ProjectOptionEntry","key":"NetworkCollapsed","context":"{2232342-19585}","value":false},{"$id":"5","$type":"ProjectOptionEntry","key":"RestoreNetworkStates","context":"{2232321-19582}","value":true},{"$id":"6","$type":"ProjectOptionEntry","key":"NetworkCollapsed","context":"{2232342-19586}","value":false},{"$id":"7","$type":"ProjectOptionEntry","key":"NetworkCollapsed","context":"{2232342-19592}","value":false},{"$id":"8","$type":"ProjectOptionEntry","key":"NetworkCollapsed","context":"{2232342-19598}","value":false},{"$id":"9","$type":"ProjectOptionEntry","key":"LastSelection@Siemens.Simatic.PlcLanguages.SCLEditor.SCLEditorView","context":"{2232321-11191}","value":{"$id":"10","$type":"SessionDataUndo","CaretPositionRC":"0, 0"}},{"$id":"11","$type":"ProjectOptionEntry","key":"LastSelection@Siemens.Simatic.PlcLanguages.PLFrame.BasicLanguageEditor","context":"{2232321-11194}","value":{"$id":"12","$type":"SessionState","NetworkStates":{"$id":"13","$type":"Dictionary`2","2":5},"FocusedComponent":4,"ComponentUndoState":{"$id":"14","$type":"FLGViewSessionState","SelectedElements":{"$type":"String[]","$values":["<?xml version=\"1.0\" encoding=\"utf-16\"?><ConnectionElement UId=\"26\" Label=\"false\" />"]},"RelevantSettings":null}}},{"$id":"15","$type":"ProjectOptionEntry","key":"NetworkCollapsed","context":"{2232342-37462}","value":false},{"$id":"16","$type":"ProjectOptionEntry","key":"NetworkCollapsed","context":"{2232342-20528}","value":false},{"$id":"17","$type":"ProjectOptionEntry","key":"RestoreNetworkStates","context":"{2232321-20525}","value":true},{"$id":"18","$type":"ProjectOptionEntry","key":"NetworkCollapsed","context":"{2232342-20532}","value":false},{"$id":"19","$type":"ProjectOptionEntry","key":"NetworkCollapsed","context":"{2232342-20538}","value":false},{"$id":"20","$type":"ProjectOptionEntry","key":"NetworkCollapsed","context":"{2232342-20614}","value":false},{"$id":"21","$type":"ProjectOptionEntry","key":"LastSelection@Siemens.Simatic.PlcLanguages.PLFrame.BasicLanguageEditor","context":"{2232321-20525}","value":{"$id":"22","$type":"SessionState","NetworkStates":{"$id":"23","$type":"Dictionary`2","1":5},"FocusedComponent":4,"ComponentUndoState":{"$id":"24","$type":"FLGViewSessionState","SelectedElements":{"$type":"String[]","$values":["<?xml version=\"1.0\" encoding=\"utf-16\"?><Connector UId=\"-14\" FormalName=\"R1\" OwnerUId=\"30\" ParaNum=\"-1\" />"]},"RelevantSettings":null}}},{"$id":"25","$type":"ProjectOptionEntry","key":"NetworkCollapsed","context":"{2232342-21555}","value":false},{"$id":"26","$type":"ProjectOptionEntry","key":"RestoreNetworkStates","context":"{2232321-21552}","value":true},{"$id":"27","$type":"ProjectOptionEntry","key":"NetworkCollapsed","context":"{2232342-21559}","value":false},{"$id":"28","$type":"ProjectOptionEntry","key":"RestoreNetworkStates","context":"{2232321-21556}","value":true},{"$id":"29","$type":"ProjectOptionEntry","key":"NetworkCollapsed","context":"{2232342-21566}","value":false},{"$id":"30","$type":"ProjectOptionEntry","key":"NetworkCollapsed","context":"{2232342-21583}","value":false},{"$id":"31","$type":"ProjectOptionEntry","key":"NetworkCollapsed","context":"{2232342-21594}","value":false},{"$id":"32","$type":"ProjectOptionEntry","key":"NetworkCollapsed","context":"{2232342-21598}","value":false},{"$id":"33","$type":"ProjectOptionEntry","key":"LastSelection@Siemens.Simatic.PlcLanguages.PLFrame.BasicLanguageEditor","context":"{2232321-21552}","value":{"$id":"34","$type":"SessionState","NetworkStates":{"$id":"35","$type":"Dictionary`2","1":5},"FocusedComponent":4,"ComponentUndoState":{"$id":"36","$type":"FLGViewSessionState","SelectedElements":{"$type":"String[]","$values":["<?xml version=\"1.0\" encoding=\"utf-16\"?><ConnectionElement UId=\"28\" Label=\"false\" />"]},"RelevantSettings":null}}},{"$id":"37","$type":"ProjectOptionEntry","key":"LastSelection@Siemens.Simatic.PlcLanguages.PLFrame.BasicLanguageEditor","context":"{2232321-29896}","value":{"$id":"38","$type":"SessionState","NetworkStates":{"$id":"39","$type":"Dictionary`2","3":5},"FocusedComponent":4,"ComponentUndoState":{"$id":"40","$type":"FLGViewSessionState","SelectedElements":{"$type":"String[]","$values":["<?xml version=\"1.0\" encoding=\"utf-16\"?><ConnectionElement UId=\"23\" Label=\"false\" />"]},"RelevantSettings":null}}},{"$id":"41","$type":"ProjectOptionEntry","key":"NetworkCollapsed","context":"{2232342-24683}","value":false},{"$id":"42","$type":"ProjectOptionEntry","key":"RestoreNetworkStates","context":"{2232321-24680}","value":true},{"$id":"43","$type":"ProjectOptionEntry","key":"NetworkCollapsed","context":"{2232342-24684}","value":false},{"$id":"44","$type":"ProjectOptionEntry","key":"LastSelection@Siemens.Simatic.PlcLanguages.PLFrame.BasicLanguageEditor","context":"{2232321-24680}","value":{"$id":"45","$type":"SessionState","NetworkStates":{"$id":"46","$type":"Dictionary`2","2":5},"FocusedComponent":4,"ComponentUndoState":{"$id":"47","$type":"FLGViewSessionState","SelectedElements":{"$type":"String[]","$values":["<?xml version=\"1.0\" encoding=\"utf-16\"?><Connector UId=\"-2\" FormalName=\"OUT1\" OwnerUId=\"21\" ParaNum=\"-1\" />"]},"RelevantSettings":null}}},{"$id":"48","$type":"ProjectOptionEntry","key":"NetworkCollapsed","context":"{2232342-25738}","value":false},{"$id":"49","$type":"ProjectOptionEntry","key":"RestoreNetworkStates","context":"{2232321-25735}","value":true},{"$id":"50","$type":"ProjectOptionEntry","key":"NetworkCollapsed","context":"{2232342-25745}","value":false},{"$id":"51","$type":"ProjectOptionEntry","key":"LastSelection@Siemens.Simatic.PlcLanguages.PLFrame.BasicLanguageEditor","context":"{2232321-25735}","value":{"$id":"52","$type":"SessionState","NetworkStates":{"$id":"53","$type":"Dictionary`2","5":5},"FocusedComponent":4,"ComponentUndoState":{"$id":"54","$type":"FLGViewSessionState","SelectedElements":{"$type":"String[]","$values":["<?xml version=\"1.0\" encoding=\"utf-16\"?><ConnectionElement UId=\"22\" Label=\"false\" />"]},"RelevantSettings":null}}},{"$id":"55","$type":"ProjectOptionEntry","key":"NetworkCollapsed","context":"{2232342-27798}","value":false},{"$id":"56","$type":"ProjectOptionEntry","key":"NetworkCollapsed","context":"{2232342-27845}","value":false},{"$id":"57","$type":"ProjectOptionEntry","key":"NetworkCollapsed","context":"{2232342-29899}","value":false},{"$id":"58","$type":"ProjectOptionEntry","key":"RestoreNetworkStates","context":"{2232321-29896}","value":true},{"$id":"59","$type":"ProjectOptionEntry","key":"NetworkCollapsed","context":"{2232342-29900}","value":false},{"$id":"60","$type":"ProjectOptionEntry","key":"NetworkCollapsed","context":"{2232342-29914}","value":false},{"$id":"61","$type":"ProjectOptionEntry","key":"NetworkCollapsed","context":"{2232342-29918}","value":false},{"$id":"62","$type":"ProjectOptionEntry","key":"NetworkCommentCollapsed","context":"{2232342-25745}","value":false},{"$id":"63","$type":"ProjectOptionEntry","key":"LastSelection@Siemens.Simatic.PlcLanguages.PLFrame.BasicLanguageEditor","context":"{2232321-21556}","value":{"$id":"64","$type":"SessionState","NetworkStates":{"$id":"65","$type":"Dictionary`2","1":5},"FocusedComponent":4,"ComponentUndoState":{"$id":"66","$type":"FLGViewSessionState","SelectedElements":{"$type":"String[]","$values":["<?xml version=\"1.0\" encoding=\"utf-16\"?><ConnectionElement UId=\"29\" Label=\"false\" />"]},"RelevantSettings":null}}},{"$id":"67","$type":"ProjectOptionEntry","key":"NetworkCollapsed","context":"{2232342-36230}","value":false},{"$id":"68","$type":"ProjectOptionEntry","key":"NetworkCollapsed","context":"{2232342-36231}","value":false},{"$id":"69","$type":"ProjectOptionEntry","key":"NetworkCollapsed","context":"{2232342-37344}","value":false},{"$id":"70","$type":"ProjectOptionEntry","key":"NetworkCollapsed","context":"{2232342-37354}","value":false},{"$id":"71","$type":"ProjectOptionEntry","key":"RestoreNetworkStates","context":"{2232321-37351}","value":true},{"$id":"72","$type":"ProjectOptionEntry","key":"NetworkCollapsed","context":"{2232342-37355}","value":false},{"$id":"73","$type":"ProjectOptionEntry","key":"NetworkCollapsed","context":"{2232342-37466}","value":false},{"$id":"74","$type":"ProjectOptionEntry","key":"NetworkCollapsed","context":"{2232342-37470}","value":false},{"$id":"75","$type":"ProjectOptionEntry","key":"NetworkCollapsed","context":"{2232342-37479}","value":false},{"$id":"76","$type":"ProjectOptionEntry","key":"NetworkCommentCollapsed","context":"{2232342-37479}","value":false},{"$id":"77","$type":"ProjectOptionEntry","key":"NetworkCollapsed","context":"{2232342-37502}","value":false},{"$id":"78","$type":"ProjectOptionEntry","key":"NetworkCollapsed","context":"{2232342-37505}","value":false},{"$id":"79","$type":"ProjectOptionEntry","key":"NetworkCollapsed","context":"{2232342-37507}","value":false},{"$id":"80","$type":"ProjectOptionEntry","key":"NetworkCollapsed","context":"{2232342-37508}","value":false},{"$id":"81","$type":"ProjectOptionEntry","key":"NetworkCollapsed","context":"{2232342-37524}","value":false},{"$id":"82","$type":"ProjectOptionEntry","key":"RestoreNetworkStates","context":"{2232321-37521}","value":true},{"$id":"83","$type":"ProjectOptionEntry","key":"NetworkCollapsed","context":"{2232342-37525}","value":false},{"$id":"84","$type":"ProjectOptionEntry","key":"LastSelection@Siemens.Simatic.PlcLanguages.PLFrame.BasicLanguageEditor","context":"{2232321-37351}","value":{"$id":"85","$type":"SessionState","NetworkStates":{"$id":"86","$type":"Dictionary`2","1":5},"FocusedComponent":4,"ComponentUndoState":{"$id":"87","$type":"FLGViewSessionState","SelectedElements":{"$type":"String[]","$values":["<?xml version=\"1.0\" encoding=\"utf-16\"?><ConnectionElement UId=\"35\" Label=\"false\" />"]},"RelevantSettings":null}}},{"$id":"88","$type":"ProjectOptionEntry","key":"LastSelection@Siemens.Simatic.PlcLanguages.PLFrame.BasicLanguageEditor","context":"{2232321-19582}","value":{"$id":"89","$type":"SessionState","NetworkStates":{"$id":"90","$type":"Dictionary`2","2":5},"FocusedComponent":4,"ComponentUndoState":{"$id":"91","$type":"FLGViewSessionState","SelectedElements":{"$type":"String[]","$values":["<?xml version=\"1.0\" encoding=\"utf-16\"?><Operand UId=\"77\" RefId=\"53\" OwnerUId=\"76\" ParaNum=\"-1\" Formalname=\"operand\" />"]},"RelevantSettings":null}}},{"$id":"92","$type":"ProjectOptionEntry","key":"LastSelection@Siemens.Simatic.PlcLanguages.PLFrame.BasicLanguageEditor","context":"{2232321-37521}","value":{"$id":"93","$type":"SessionState","NetworkStates":{"$id":"94","$type":"Dictionary`2","1":5},"FocusedComponent":4,"ComponentUndoState":{"$id":"95","$type":"FLGViewSessionState","SelectedElements":{"$type":"String[]","$values":["<?xml version=\"1.0\" encoding=\"utf-16\"?><Connector UId=\"-4\" FormalName=\"IN\" OwnerUId=\"23\" ParaNum=\"-1\" />"]},"RelevantSettings":null}}}]}